qbirthday/__about__.py
qbirthday/__init__.py
qbirthday/aboutdialog.py
qbirthday/birthday_list.py
qbirthday/exceptions.py
qbirthday/ics_export.py
qbirthday/mainwindow.py
qbirthday/paths.py
qbirthday/preferencesdialog.py
qbirthday/settings.py
qbirthday/statusicon.py
qbirthday/backends/__init__.py
qbirthday/backends/base.py
qbirthday/backends/csv.py
qbirthday/backends/exceptions.py
qbirthday/backends/lightning.py
qbirthday/backends/mysql.py
qbirthday/i18n/qbirthday_fr.qm
qbirthday/i18n/qbirthday_fr.ts
qbirthday/pics/birthday.png
qbirthday/pics/birthdaylost.png
qbirthday/pics/birthdaynext.png
qbirthday/pics/birthdayred.png
qbirthday/pics/birthdaytoday.png
qbirthday/pics/nobirthday.png
qbirthday/pics/qbirthday.png
qbirthday/ui/aboutdialog.ui
qbirthday/ui/csvpreferencesdialog.ui
qbirthday/ui/icsexportpreferencesdialog.ui
qbirthday/ui/mainwindow.ui
qbirthday/ui/mysqlpreferencesdialog.ui
qbirthday/ui/preferencesdialog.ui
qbirthday-0.7.1.dist-info/entry_points.txt
qbirthday-0.7.1.dist-info/LICENSE
qbirthday-0.7.1.dist-info/WHEEL
qbirthday-0.7.1.dist-info/METADATA
qbirthday-0.7.1.dist-info/RECORD
