Metadata-Version: 2.3
Name: qbirthday
Version: 0.7.1
Summary: QBirthday birthday reminder
Author-email: Jérôme Lafréchoux <jerome@jolimont.fr>
Maintainer-email: Jérôme Lafréchoux <jerome@jolimont.fr>
Requires-Python: >=3.9
Classifier: Development Status :: 5 - Production/Stable
Classifier: Intended Audience :: End Users/Desktop
Classifier: Environment :: X11 Applications :: Qt
Classifier: License :: OSI Approved :: GNU General Public License v2 or later (GPLv2+)
Classifier: Operating System :: POSIX :: Linux
Classifier: Programming Language :: Python :: 3.9
Classifier: Programming Language :: Python :: 3.10
Classifier: Programming Language :: Python :: 3.11
Classifier: Programming Language :: Python :: 3.12
Classifier: Programming Language :: Python :: 3.13
Requires-Dist: PyQt5>=5.15
Project-URL: Changelog, https://github.com/lafrech/qbirthday/blob/master/CHANGELOG.rst
Project-URL: Issues, https://github.com/lafrech/qbirthday/issues
Project-URL: Source, https://github.com/lafrech/qbirthday
